README.md
setup.py
trackme/__init__.py
trackme/app.py
trackme/config.py
trackme/db_connect.py
trackme/forms.py
trackme/main_parsing.py
trackme/ukr_stemmer.py
trackme.egg-info/PKG-INFO
trackme.egg-info/SOURCES.txt
trackme.egg-info/dependency_links.txt
trackme.egg-info/requires.txt
trackme.egg-info/top_level.txt
trackme/classes/KeywordsADT.py
trackme/classes/__init__.py
trackme/classes/keyword.py
trackme/classes/user.py
trackme/telegram_parsing/__init__.py
trackme/telegram_parsing/channels.py
trackme/telegram_parsing/tg_parse.py
trackme/twitter_parsing/__init__.py
trackme/twitter_parsing/twitter_parse.py