Metadata-Version: 2.1
Name: trackme
Version: 1.0.4
Summary: Social media monitoring
Home-page: https://github.com/DmytroLopushanskyy/Social-Media-Monitoring
Author: Bohdan Vey and Dmytro Lopushanskyy
License: UNKNOWN
Platform: UNKNOWN
Classifier: Programming Language :: Python :: 3
Classifier: License :: OSI Approved :: MIT License
Classifier: Operating System :: OS Independent
Requires-Python: >=3.6
